[
  {
    "region": "US",
    "provider_name": "Netflix",
    "provider_id": 8
  },
  {
    "region": "US",
    "provider_name": "Apple TV+",
    "provider_id": 350
  },

  {
    "region": "US",
    "provider_name": "Adult Swim",
    "provider_id": 318
  },
  {
    "region": "US",
    "provider_name": "Max",
    "provider_id": 1899
  },
  {
    "region": "US",
    "provider_name": "Amazon Prime Video",
    "provider_id": 9
  },

  {
    "region": "FR",
    "provider_name": "Canal+ Premium",
    "provider_id": 2101
  }
]
